{
    "backend": "flask",
    "db_name": "",
    "db_pass": "",
    "db_type": "",
    "db_user": "",
    "dbms": "0",
    "description": "generated product",
    "design": "material-kit",
    "docker": "0",
    "err_code": 0,
    "frontend": "",
    "github_repo": "https://github.com/appseed-projects/ebf53452-4f0a-4706-b46a-0de88ebbbd82",
    "heroku": "0",
    "pattern": "mvc",
    "pro": "0",
    "task_id": "ebf53452-4f0a-4706-b46a-0de88ebbbd82",
    "task_info": "Upload Sources [0%] - 335 files",
    "task_output": "ebf53452-4f0a-4706-b46a-0de88ebbbd82.zip",
    "task_result": "SUCCESS",
    "task_state": "RUNNING",
    "task_ts_end": "2022-05-19-02-53-12",
    "task_ts_start": "2022-05-19-02-53-11"
}